docs/source/conf.py
simulstream/__init__.py
simulstream/config.py
simulstream/inference.py
simulstream/client/__init__.py
simulstream/client/wav_reader_client.py
simulstream/metrics/__init__.py
simulstream/metrics/detokenizers.py
simulstream/metrics/logger.py
simulstream/metrics/readers.py
simulstream/metrics/score_latency.py
simulstream/metrics/score_quality.py
simulstream/metrics/stats.py
simulstream/metrics/scorers/__init__.py
simulstream/metrics/scorers/latency/__init__.py
simulstream/metrics/scorers/latency/mwersegmenter.py
simulstream/metrics/scorers/latency/stream_laal.py
simulstream/metrics/scorers/quality/__init__.py
simulstream/metrics/scorers/quality/comet.py
simulstream/metrics/scorers/quality/mwersegmenter.py
simulstream/metrics/scorers/quality/sacrebleu.py
simulstream/server/__init__.py
simulstream/server/http_server.py
simulstream/server/message_processor.py
simulstream/server/websocket_server.py
simulstream/server/speech_processors/__init__.py
simulstream/server/speech_processors/base.py
simulstream/server/speech_processors/base_streamatt.py
simulstream/server/speech_processors/canary_sliding_window_retranslation.py
simulstream/server/speech_processors/hf_sliding_window_retranslation.py
simulstream/server/speech_processors/incremental_output.py
simulstream/server/speech_processors/seamless_sliding_window_retranslation.py
simulstream/server/speech_processors/seamless_streamatt.py
simulstream/server/speech_processors/simuleval_wrapper.py
simulstream/server/speech_processors/sliding_window_retranslation.py
simulstream/server/speech_processors/vad_wrapper.py
simulstream-0.1.0.dist-info/licenses/LICENSE
uts/__init__.py
uts/utils.py
uts/metrics/__init__.py
uts/metrics/log_reader.py
uts/speech_processors/__init__.py
uts/speech_processors/test_simuleval_wrapper.py
simulstream-0.1.0.dist-info/METADATA
simulstream-0.1.0.dist-info/WHEEL
simulstream-0.1.0.dist-info/entry_points.txt
simulstream-0.1.0.dist-info/top_level.txt
simulstream-0.1.0.dist-info/RECORD
