Metadata-Version: 2.4
Name: simulstream
Version: 0.1.0
Summary: A server to run simultaneous/streaming experiments and demo
Author-email: Marco Gaido <mgaido@fbk.eu>, FBK HLT-MT <mt@fbk.eu>
License:                                  Apache License
Project-URL: GitHub, https://github.com/hlt-mt/simulstream
Project-URL: Issues, https://github.com/hlt-mt/simulstream/issues
Keywords: simultaneous,demo,websocket,streaming
Requires-Python: >=3.9
License-File: LICENSE
Requires-Dist: pyyaml>6.0
Requires-Dist: websockets
Requires-Dist: torch
Requires-Dist: librosa
Provides-Extra: dev
Requires-Dist: pytest==7.4.0; extra == "dev"
Requires-Dist: flake8; extra == "dev"
Requires-Dist: sphinx; extra == "dev"
Requires-Dist: sphinx-rtd-theme; extra == "dev"
Requires-Dist: build; extra == "dev"
Requires-Dist: twine; extra == "dev"
Provides-Extra: hf
Requires-Dist: transformers==4.48.1; extra == "hf"
Provides-Extra: canary
Requires-Dist: Cython; extra == "canary"
Requires-Dist: nemo_toolkit[asr]==2.4.0; extra == "canary"
Provides-Extra: vad
Requires-Dist: silero-vad; extra == "vad"
Provides-Extra: eval
Requires-Dist: unbabel-comet==2.2.6; extra == "eval"
Requires-Dist: mweralign; extra == "eval"
Requires-Dist: sacrebleu; extra == "eval"
Dynamic: license-file
